Metadata-Version: 2.2
Name: GetInformationUserID
Version: 0.1
Summary: Получение информации по айди подьзователя, для вывода в основной код Telethon.
Author: Puxxalwl
Author-email: ruslan544mc@gmail.com
License: MIT
Classifier: Programming Language :: Python :: 3
Classifier: License :: OSI Approved :: MIT License
Classifier: Operating System :: OS Independent
Requires-Python: >=3.6
License-File: LICENSE
Requires-Dist: Telethon
Dynamic: author
Dynamic: author-email
Dynamic: classifier
Dynamic: license
Dynamic: requires-dist
Dynamic: requires-python
Dynamic: summary
